maxo/__init__.py
maxo/setup.py
maxo-0.1.0.dist-info/METADATA
maxo-0.1.0.dist-info/WHEEL
maxo-0.1.0.dist-info/RECORD
