Metadata-Version: 2.4
Name: maxo
Version: 0.1.0
Summary: заглушка
Author-email: Kirill Lesovoy <kirill.lesovoi@mail.ru>
License: MIT
Classifier: Programming Language :: Python :: 3
Requires-Python: >=3.12
